cloudkittyclient/__init__.py
cloudkittyclient/auth.py
cloudkittyclient/client.py
cloudkittyclient/exc.py
cloudkittyclient/format.py
cloudkittyclient/osc.py
cloudkittyclient/shell.py
cloudkittyclient/utils.py
cloudkittyclient/common/__init__.py
cloudkittyclient/common/base.py
cloudkittyclient/common/client.py
cloudkittyclient/tests/__init__.py
cloudkittyclient/tests/utils.py
cloudkittyclient/tests/functional/__init__.py
cloudkittyclient/tests/functional/base.py
cloudkittyclient/tests/functional/v1/__init__.py
cloudkittyclient/tests/functional/v1/test_collector.py
cloudkittyclient/tests/functional/v1/test_hashmap.py
cloudkittyclient/tests/functional/v1/test_info.py
cloudkittyclient/tests/functional/v1/test_pyscripts.py
cloudkittyclient/tests/functional/v1/test_rating.py
cloudkittyclient/tests/functional/v1/test_report.py
cloudkittyclient/tests/functional/v1/test_storage.py
cloudkittyclient/tests/functional/v2/__init__.py
cloudkittyclient/tests/functional/v2/test_dataframes.py
cloudkittyclient/tests/functional/v2/test_scope.py
cloudkittyclient/tests/functional/v2/test_summary.py
cloudkittyclient/tests/unit/__init__.py
cloudkittyclient/tests/unit/v1/__init__.py
cloudkittyclient/tests/unit/v1/base.py
cloudkittyclient/tests/unit/v1/test_collector.py
cloudkittyclient/tests/unit/v1/test_hashmap.py
cloudkittyclient/tests/unit/v1/test_info.py
cloudkittyclient/tests/unit/v1/test_pyscripts.py
cloudkittyclient/tests/unit/v1/test_rating.py
cloudkittyclient/tests/unit/v1/test_report.py
cloudkittyclient/tests/unit/v1/test_report_cli.py
cloudkittyclient/tests/unit/v1/test_storage.py
cloudkittyclient/tests/unit/v2/__init__.py
cloudkittyclient/tests/unit/v2/base.py
cloudkittyclient/tests/unit/v2/test_dataframes.py
cloudkittyclient/tests/unit/v2/test_rating.py
cloudkittyclient/tests/unit/v2/test_scope.py
cloudkittyclient/tests/unit/v2/test_summary.py
cloudkittyclient/v1/__init__.py
cloudkittyclient/v1/client.py
cloudkittyclient/v1/collector.py
cloudkittyclient/v1/collector_cli.py
python_cloudkittyclient-6.0.0.dist-info/licenses/AUTHORS
python_cloudkittyclient-6.0.0.dist-info/licenses/LICENSE
python_cloudkittyclient-6.0.0.dist-info/METADATA
python_cloudkittyclient-6.0.0.dist-info/WHEEL
python_cloudkittyclient-6.0.0.dist-info/entry_points.txt
python_cloudkittyclient-6.0.0.dist-info/pbr.json
python_cloudkittyclient-6.0.0.dist-info/top_level.txt
python_cloudkittyclient-6.0.0.dist-info/RECORD
