Metadata-Version: 2.4
Name: python-cloudkittyclient
Version: 6.0.0
Summary: API client of cloudkitty, Rating as a Service project.
Home-page: https://docs.openstack.org/python-cloudkittyclient/latest/
Author: OpenStack
Author-email: openstack-discuss@lists.openstack.org
Classifier: Environment :: OpenStack
Classifier: Intended Audience :: Information Technology
Classifier: Intended Audience :: System Administrators
Classifier: License :: OSI Approved :: Apache Software License
Classifier: Operating System :: POSIX :: Linux
Classifier: Programming Language :: Python
Classifier: Programming Language :: Python :: 3 :: Only
Classifier: Programming Language :: Python :: Implementation :: CPython
Classifier: Programming Language :: Python :: 3
Classifier: Programming Language :: Python :: 3.10
Classifier: Programming Language :: Python :: 3.11
Classifier: Programming Language :: Python :: 3.12
Requires-Python: >=3.10
License-File: LICENSE
License-File: AUTHORS
Requires-Dist: pbr>=5.5.1
Requires-Dist: cliff>=3.5.0
Requires-Dist: keystoneauth1>=4.3.0
Requires-Dist: oslo.utils>=4.7.0
Requires-Dist: oslo.log>=4.4.0
Requires-Dist: PyYAML>=5.3.1
Requires-Dist: jsonpath-rw-ext>=1.2.0
Requires-Dist: openstacksdk>=0.10.0
Requires-Dist: osc-lib>=2.3.0
Dynamic: author
Dynamic: author-email
Dynamic: classifier
Dynamic: description
Dynamic: home-page
Dynamic: license-file
Dynamic: requires-dist
Dynamic: requires-python
Dynamic: summary
